capitalise_delimit/__init__.py
capitalise_delimit/capitalise_delimit.py
capitalise_delimit-0.1.2.dist-info/LICENSE
capitalise_delimit-0.1.2.dist-info/METADATA
capitalise_delimit-0.1.2.dist-info/WHEEL
capitalise_delimit-0.1.2.dist-info/top_level.txt
capitalise_delimit-0.1.2.dist-info/RECORD
