Metadata-Version: 2.1
Name: capitalise-delimit
Version: 0.1.2
Summary: Capitalise string by delimiters
Home-page: https://github.com/jkoninger/capitalise-delimit
Author: Jahan Köninger
Author-email: jck999992@gmail.com
License: MIT
Platform: UNKNOWN
Classifier: Intended Audience :: Developers
Classifier: License :: OSI Approved :: MIT License
Classifier: Programming Language :: Python
Classifier: Programming Language :: Python :: 3
Classifier: Programming Language :: Python :: 3.9
Classifier: Programming Language :: Python :: 3.10
Classifier: Operating System :: OS Independent
License-File: LICENSE
